broadcast_service/__init__.py
broadcast_service/_core.py
broadcast_service/logger.py
broadcast_service/singleton.py
tests/__init__.py
tests/test_async.py
tests/test_base.py
tests/test_publisher_callback.py
broadcast_service-2.1.0.dist-info/LICENSE
broadcast_service-2.1.0.dist-info/METADATA
broadcast_service-2.1.0.dist-info/WHEEL
broadcast_service-2.1.0.dist-info/top_level.txt
broadcast_service-2.1.0.dist-info/RECORD
