Metadata-Version: 2.1
Name: broadcast-service
Version: 2.1.0
Summary: A lightweight third-party broadcast/pubsub library
Home-page: https://github.com/Undertone0809/broadcast-service
Author: Zeeland
Author-email: zeeland@foxmail.com
License: Apache 2.0
Keywords: broadcast,broadcast-service,publisher,subscriber,pubsub
Classifier: Development Status :: 3 - Alpha
Classifier: Intended Audience :: Developers
Classifier: Programming Language :: Python :: 3
Classifier: Programming Language :: Python :: 3.7
Classifier: Programming Language :: Python :: 3.8
Classifier: Programming Language :: Python :: 3.9
Classifier: Programming Language :: Python :: 3.10
Classifier: Programming Language :: Python :: 3 :: Only
Classifier: License :: OSI Approved :: MIT License
Classifier: Operating System :: OS Independent
Requires-Python: >=3.6
License-File: LICENSE
Requires-Dist: pydantic
Requires-Dist: cushy-storage
